{"start-docs_b-js_http(s)及缓存机制.md":"68a4dd93","start-docs_b-js_bind_call_apply.md":"2e62cda2","start-docs_b-js_单例模式和工厂模式.md":"d425c6fc","start-docs_b-js__js与native通信.md":"d18c14bf","start-docs_b-js_js中的new干了什么.md":"ddae5144","start-docs_b-js_js作用域.md":"711ac718","start-docs_b-js_js继承.md":"a7704e6b","start-docs_b-js_js对象拷贝及深拷贝.md":"dab21dc0","start-docs_a-数据结构_递归和分治.md":"9ad72c48","start-docs_b-js_promise原理及实现.md":"17747137","start-docs_b-js_js垃圾回收机制.md":"12bfcbd9","start-docs_a-数据结构__哈希表.md":"9c62a353","start-docs_a-数据结构_数据类型.md":"b4c743a3","start-docs_b-js_vuex或redux.md":"e642a0b1","index.md":"0687bdf6","start-docs_b-js_制作cli.md":"12e8c74c","start-docs_b-js_with语法.md":"5fef8412","start-docs_b-js_settimeout.md":"7257c30e","start-docs_b-js_前端网络安全.md":"0662afd3","start-docs_a-数据结构_堆栈和队列.md":"88ddbb9b","start-docs_b-js_vue-router或react-router.md":"ec2bedcd","start-docs_b-js_npm包管理.md":"a7e5f0eb","start-docs_a-数据结构__blog.md":"99f7cbc5","start-docs_b-js_lhs和rhs.md":"08a6f1ad","start-docs_b-js_js的this关键字.md":"706dd4bc","start-docs_a-数据结构_数组的全部方法.md":"5cb51803","start-docs_b-js_js常用逻辑题.md":"3f40dc3b","repl.md":"794ebfb9","start-docs_a-数据结构_二叉树.md":"0ec09c64","start-docs_b-js_weakref.md":"f8604ad1","start-docs_a-数据结构_深、广优先遍历.md":"eeb6e999","start-docs_a-数据结构_排序.md":"066c3b0c","start-docs_a-数据结构__动态规划和贪心算法.md":"2681b941","start-docs_b-js_从url到显示网页的全过程.md":"e5da68af","start-docs_b-js_class与函数.md":"ef57222d","start-docs_a-数据结构_链表.md":"52222e84","start-docs_b-js_eventbus.md":"c683df20","start-docs_b-js_设计模式.md":"21f69ac8","start-docs_b-js_节流-防抖.md":"aa78299f","start-docs_b-js_观察者模式及发布订阅者模式.md":"eaba303e","start-docs_b-js_纯函数与副作用函数.md":"0f6933f1","start-docs_b-js_柯里化.md":"39147681","start-docs_b-js_模块化及打包模式.md":"c2797047","start-docs_b-js_箭头函数与普通函数.md":"2a7c4865","start-docs_g-打包工具_iife.md":"cf64f2ba","start-docs_b-js_检测数组类型的几种方式.md":"2505f246","start-docs_b-js_请求并行串行问题及复用.md":"b551d463","start-docs_f-css_1px.md":"18682060","start-docs_f-css_选择器层级.md":"3a5e95cd","start-docs_d-html_栅格系统.md":"d44d102d","start-docs_d-html_什么是语义化标签.md":"2784307c","start-docs_d-html__blog.md":"37b968d5","start-docs_f-css_保持宽高比.md":"5c4d4752","start-docs_index.md":"fe4a46af","start-docs_f-css_属性计算过程.md":"bd60186b","start-docs_f-css_bfc.md":"64acd712","start-docs_b-js_长列表渲染优化.md":"5ad73580","start-docs_f-css_哪些属性可以继承.md":"092ce307","start-docs_b-js_常用方法原理实现.md":"542e9b6f","start-docs_g-打包工具_esbuild.md":"15025b3b","start-docs_quickentry.md":"8c083369","start-docs_d-html_svg是什么.md":"d2171768","start-docs_h-python_内置方法常用.md":"9780e7c8","start-docs_create-blog.md":"43c2844e","start-docs_g-打包工具_vite.md":"344b067f","start-docs_g-打包工具_webpack.md":"b69d1112","start-docs_h-python_数据类型.md":"76db846d","start-docs_h-python_文件内变量.md":"39658cbc","start-docs_f-css_盒模型.md":"ebd700d2","start-docs_d-html_什么是xml.md":"f8af8a22","start-docs_g-打包工具_rollup.md":"87072856"}
